clouds2mask/__init__.py
clouds2mask/build_vrt.py
clouds2mask/cloud_mask.py
clouds2mask/cloud_mask_linear.py
clouds2mask/download_model_weights.py
clouds2mask/inference.py
clouds2mask/make_qml_files.py
clouds2mask/model_download_links.csv
clouds2mask/model_helpers.py
clouds2mask/model_settings.py
clouds2mask/patch_generator.py
clouds2mask/pred_joiner.py
clouds2mask/processing_settings.py
clouds2mask/tta_helpers.py
clouds2mask-1.1.3.dist-info/LICENSE
clouds2mask-1.1.3.dist-info/METADATA
clouds2mask-1.1.3.dist-info/WHEEL
clouds2mask-1.1.3.dist-info/top_level.txt
clouds2mask-1.1.3.dist-info/RECORD
