Metadata-Version: 2.1
Name: clouds2mask
Version: 1.1.3
Summary: Python library for cloud and cloud shadow segmentation in Sentinel-2
Home-page: https://github.com/DPIRD-DMA/CloudS2Mask
Author: Nick Wright
Author-email: nicholas.wright@dpird.wa.gov.au
Classifier: Development Status :: 3 - Alpha
Classifier: Intended Audience :: Developers
Classifier: License :: OSI Approved :: MIT License
Classifier: Programming Language :: Python :: 3.7
Classifier: Programming Language :: Python :: 3.8
Requires-Python: >=3.7
License-File: LICENSE
Requires-Dist: fastai >=2.7
Requires-Dist: timm <1.0.4,>=0.9
Requires-Dist: tqdm >=4.0
Requires-Dist: rasterio >=1.3
Requires-Dist: gdown >=5.1.0
